{"stats":{"minecraft:mined":{"minecraft:granite":9,"enhanced_minecraft:saphire_ore":5},"minecraft:picked_up":{"enhanced_minecraft:raw_saphire":13,"minecraft:granite":9,"enhanced_minecraft:saphire":2},"minecraft:custom":{"minecraft:jump":5,"minecraft:time_since_rest":5208,"minecraft:leave_game":3,"minecraft:play_time":5208,"minecraft:time_since_death":5208,"minecraft:walk_on_water_one_cm":2542,"minecraft:walk_one_cm":914,"minecraft:sneak_time":142,"minecraft:total_world_time":35687,"minecraft:walk_under_water_one_cm":695,"minecraft:fly_one_cm":2409},"minecraft:used":{"enhanced_minecraft:bronzium_pickaxe":14}},"DataVersion":3465}